tests/__init__.py
tests/httpoperationtest.py
tests/replicatortest.py
tests/resultvalidatortest.py
tests/strutilstest.py
tntfuzzer/__init__.py
tntfuzzer/httpoperation.py
tntfuzzer/replicator.py
tntfuzzer/resultvalidatior.py
tntfuzzer/strutils.py
tntfuzzer/tntfuzzer.py
tntfuzzer-1.0.0.dist-info/DESCRIPTION.rst
tntfuzzer-1.0.0.dist-info/METADATA
tntfuzzer-1.0.0.dist-info/RECORD
tntfuzzer-1.0.0.dist-info/WHEEL
tntfuzzer-1.0.0.dist-info/entry_points.txt
tntfuzzer-1.0.0.dist-info/metadata.json
tntfuzzer-1.0.0.dist-info/top_level.txt
