Metadata-Version: 2.0
Name: tntfuzzer
Version: 1.0.0
Summary: An OpenAPI (Swagger) fuzzer written in python. Basically TnT for your API.
Home-page: https://github.com/Teebytes/TnT-Fuzzer
Author: Tobias Hassenkloever
Author-email: tnt@teebytes.net
License: UNKNOWN
Keywords: openapi,swagger,fuzzer,fuzzing,json-api,REST
Platform: UNKNOWN
Requires-Dist: GitPython (==2.1.5)
Requires-Dist: PyJFuzz (==1.1.0)
Requires-Dist: PyYAML (==3.12)
Requires-Dist: bottle (==0.12.13)
Requires-Dist: bravado (==9.1.0)
Requires-Dist: bravado-core (==4.8.4)
Requires-Dist: certifi (==2017.7.27.1)
Requires-Dist: chardet (==3.0.4)
Requires-Dist: funcsigs (==1.0.2)
Requires-Dist: functools32 (==3.2.3.post2)
Requires-Dist: gitdb2 (==2.0.2)
Requires-Dist: gramfuzz (==1.2.0)
Requires-Dist: idna (==2.6)
Requires-Dist: jsonschema (==2.6.0)
Requires-Dist: mock (==2.0.0)
Requires-Dist: netifaces (==0.10.6)
Requires-Dist: nose (==1.3.7)
Requires-Dist: pbr (==3.1.1)
Requires-Dist: python-dateutil (==2.6.1)
Requires-Dist: pytz (==2017.2)
Requires-Dist: requests (==2.18.4)
Requires-Dist: rfc3987 (==1.3.7)
Requires-Dist: simplejson (==3.11.1)
Requires-Dist: six (==1.10.0)
Requires-Dist: smmap2 (==2.0.3)
Requires-Dist: strict-rfc3339 (==0.7)
Requires-Dist: swagger-spec-validator (==2.1.0)
Requires-Dist: termcolor (==1.1.0)
Requires-Dist: urllib3 (==1.22)
Requires-Dist: webcolors (==1.7)
